b2btest_audio/__init__.py
b2btest_audio/diffaudio.py
b2btest_audio/diffaudio_test.py
b2btest_audio-1.4.3.dist-info/METADATA
b2btest_audio-1.4.3.dist-info/WHEEL
b2btest_audio-1.4.3.dist-info/entry_points.txt
b2btest_audio-1.4.3.dist-info/top_level.txt
b2btest_audio-1.4.3.dist-info/RECORD
