Metadata-Version: 2.1
Name: b2btest-audio
Version: 1.4.3
Summary: Audio file support for b2btest, a framework to test against checked outputs
Home-page: https://github.com/vokimon/back2back_audio
Author: David Garcia Garzon
Author-email: voki@canvoki.net
License: GNU General Public License v3 or later (GPLv3+)
Classifier: Programming Language :: Python
Classifier: Programming Language :: Python :: 2
Classifier: Programming Language :: Python :: 3
Classifier: Topic :: Software Development :: Libraries :: Python Modules
Classifier: Intended Audience :: Developers
Classifier: Development Status :: 5 - Production/Stable
Classifier: License :: OSI Approved :: GNU General Public License v3 or later (GPLv3+)
Classifier: Operating System :: OS Independent
Requires-Python: >=3.9
Requires-Dist: setuptools>40.5
Requires-Dist: b2btest>=1.4
Requires-Dist: wavefile
